ipydagred3/__init__.py
ipydagred3/_version.py
ipydagred3/edge.py
ipydagred3/graph.py
ipydagred3/node.py
ipydagred3/widget.py
ipydagred3/extension/install.json
ipydagred3/extension/ipydagred3.json
ipydagred3/labextension/package.json
ipydagred3/labextension/static/480.30aed820b54ae41a7e42.js
ipydagred3/labextension/static/504.f43a702b745b660159bd.js
ipydagred3/labextension/static/518.38dee5c8babfd53ca930.js
ipydagred3/labextension/static/526.c385ed90fc58df1b45fa.js
ipydagred3/labextension/static/568.c652f4703c9c7d0b144d.js
ipydagred3/labextension/static/605.c8f155095e5e3b359fe9.js
ipydagred3/labextension/static/790.c0f0d326e64eae110eb5.js
ipydagred3/labextension/static/790.c0f0d326e64eae110eb5.js.LICENSE.txt
ipydagred3/labextension/static/793.0b72fa86f3e6beb084d3.js
ipydagred3/labextension/static/823.45b3a0a1f9d928cea464.js
ipydagred3/labextension/static/remoteEntry.ce338f0c0c19ff113755.js
ipydagred3/labextension/static/style.js
ipydagred3/labextension/static/third-party-licenses.json
ipydagred3/nbextension/__init__.py
ipydagred3/nbextension/static/extension.js
ipydagred3/nbextension/static/index.js
ipydagred3/nbextension/static/index.js.map
ipydagred3/tests/__init__.py
ipydagred3/tests/conftest.py
ipydagred3/tests/test_nbextension_path.py
ipydagred3-0.4.1.data/data/share/jupyter/labextensions/ipydagred3/package.json
ipydagred3-0.4.1.data/data/share/jupyter/labextensions/ipydagred3/static/480.30aed820b54ae41a7e42.js
ipydagred3-0.4.1.data/data/share/jupyter/labextensions/ipydagred3/static/504.f43a702b745b660159bd.js
ipydagred3-0.4.1.data/data/share/jupyter/labextensions/ipydagred3/static/518.38dee5c8babfd53ca930.js
ipydagred3-0.4.1.data/data/share/jupyter/labextensions/ipydagred3/static/526.c385ed90fc58df1b45fa.js
ipydagred3-0.4.1.data/data/share/jupyter/labextensions/ipydagred3/static/568.c652f4703c9c7d0b144d.js
ipydagred3-0.4.1.data/data/share/jupyter/labextensions/ipydagred3/static/605.c8f155095e5e3b359fe9.js
ipydagred3-0.4.1.dist-info/METADATA
ipydagred3-0.4.1.dist-info/WHEEL
ipydagred3-0.4.1.dist-info/licenses/LICENSE
ipydagred3-0.4.1.dist-info/RECORD
